rf24_py-0.5.0.dist-info/METADATA
rf24_py-0.5.0.dist-info/WHEEL
rf24_py-0.5.0.dist-info/licenses/LICENSE
rf24_py/__init__.py
rf24_py/__init__.pyi
rf24_py/py.typed
rf24_py/rf24_py.abi3.so
rf24_py-0.5.0.dist-info/RECORD
