Metadata-Version: 2.4
Name: rf24-py
Version: 0.5.0
Classifier: Programming Language :: Rust
Classifier: Programming Language :: Python :: Implementation :: CPython
Classifier: Programming Language :: Python :: Implementation :: PyPy
Classifier: Development Status :: 3 - Alpha
Classifier: Intended Audience :: Developers
Classifier: Operating System :: POSIX :: Linux
Classifier: Programming Language :: C++
Classifier: Programming Language :: Python :: 3
Classifier: Topic :: Software Development :: Libraries
Classifier: Topic :: System :: Hardware
Classifier: Topic :: System :: Hardware :: Hardware Drivers
Classifier: Topic :: System :: Networking
Classifier: Typing :: Typed
License-File: LICENSE
Summary: A python package binding the nRF24/rf24-rs rust project.
Keywords: nrf24l01,nRF24L01+,raspberry,pi,linux,driver,radio,transceiver,RF24
Author-email: Brendan Doherty <2bndy5@gmail.com>
License-Expression: MIT
Requires-Python: >=3.9
Project-URL: Documentation, https://rf24-rs.readthedocs.io/en/latest
Project-URL: Source, https://github.com/nRF24/rf24-rs
Project-URL: Tracker, https://github.com/nRF24/rf24-rs/issues
